LICENSE
README.md
decouphage
setup.py
decouphage.egg-info/PKG-INFO
decouphage.egg-info/SOURCES.txt
decouphage.egg-info/dependency_links.txt
decouphage.egg-info/requires.txt
decouphage.egg-info/top_level.txt
src/__init__.py
src/annotate.py
src/core.py
src/database.py
src/output.py
src/pipeline.py
src/tools.py