Metadata-Version: 2.1
Name: decouphage
Version: 0.0.5
Summary: decouphage - A tool to annotate phage genomes.
Home-page: https://github.com/voorloopnul/decouphage
Author: Ricardo Pascal
Author-email: voorloop@gmail.com
License: UNKNOWN
Platform: UNKNOWN
Requires-Python: >=3.4
License-File: LICENSE
